s_tool/__init__.py
s_tool/core.py
s_tool/driver.py
s_tool/exceptions.py
s_tool/logger.py
s_tool/parser.py
s_tool-0.0.5.dist-info/LICENSE
s_tool-0.0.5.dist-info/METADATA
s_tool-0.0.5.dist-info/WHEEL
s_tool-0.0.5.dist-info/RECORD
