Metadata-Version: 2.1
Name: s-tool
Version: 0.0.5
Summary: Selenium wrapper to make your life easy.
Home-page: https://github.com/Python-World/s-tool
License: MIT
Keywords: Python,Selenium,wrapper,Webdriver,Tools,Utilities
Author: Ravishankar Chavare
Author-email: chavare.ravi123@gmail.com
Requires-Python: >=3.11,<4.0
Classifier: Development Status :: 4 - Beta
Classifier: Intended Audience :: Education
Classifier: Intended Audience :: Information Technology
Classifier: License :: OSI Approved :: MIT License
Classifier: Natural Language :: English
Classifier: Operating System :: OS Independent
Classifier: Programming Language :: Python
Classifier: Programming Language :: Python :: 3
Classifier: Programming Language :: Python :: 3.11
Requires-Dist: lxml (>=4.9.2,<5.0.0)
Requires-Dist: selenium (>=4.9.1,<5.0.0)
Requires-Dist: webdriver-manager (>=3.8.5,<4.0.0)
Project-URL: Repository, https://github.com/Python-World/s-tool
